{"Result":"{\"projectName\":\"\",\"ownerInfo\":\"\",\"spaceInfo\":{\"floorArea\":8.2,\"ceilingArea\":8.2,\"wallArea\":34},\"picList\":{\"effectpicPath\":{\"imagePath\":\"/public/repository/5c15/afc7/4ea4/4746/8d55/4ccc/56f1/9899/preview/image.jpg\",\"previewPath\":\"/public/repository/5c15/afc7/4ea4/4746/8d55/4ccc/56f1/9899/preview/image.jpg\",\"thumbnailPath\":\"/public/repository/5c15/afc7/4ea4/4746/8d55/4ccc/56f1/9899/preview/preview.jpg\"},\"planPath\":{\"imagePath\":\"/public/repository/e19b/1f3d/3106/4866/bc35/6df7/4215/3ec0/renderinfo/topview.jpg\",\"previewPath\":\"/public/repository/e19b/1f3d/3106/4866/bc35/6df7/4215/3ec0/renderinfo/topview.jpg\",\"thumbnailPath\":\"/public/repository/e19b/1f3d/3106/4866/bc35/6df7/4215/3ec0/renderinfo/topviewpre.jpg\"},\"airviewPath\":{\"imagePath\":\"/public/repository/e19b/1f3d/3106/4866/bc35/6df7/4215/3ec0/renderinfo/topcamera.jpg\",\"previewPath\":\"/public/repository/e19b/1f3d/3106/4866/bc35/6df7/4215/3ec0/renderinfo/topcamera.jpg\",\"thumbnailPath\":\"/public/repository/e19b/1f3d/3106/4866/bc35/6df7/4215/3ec0/renderinfo/topcamerapre.jpg\"}},\"materialList\":[{\"recommend\":false,\"id\":\"be6e9ee8-388d-42a0-bce1-b842436a215f\",\"count\":91,\"total\":9,\"unit\":\"平方米\",\"unitPrice\":1323.3,\"totalPrice\":11909.7,\"discounts\":\"可预约团购\",\"help\":\"\",\"productModel\":\"COP8001\",\"brandName\":\"裕景陶瓷\",\"brandID\":\"folder201409241427529172037\",\"name\":\"地砖\",\"info\":[{\"name\":\"勾缝剂\",\"productModel\":\"常规\",\"brandName\":\"飞鹿体验\",\"brandID\":\"folder20138261029309087627570\",\"id\":\"be6e9ee8-388d-42a0-bce1-b842436a215f-cr\",\"count\":9,\"total\":9,\"unit\":\"平方米\",\"unitPrice\":\"面议\",\"totalPrice\":\"面议\",\"discounts\":\"可预约团购\",\"help\":\"是一种以水泥为基材的固体粉末。主要用于墙砖、地砖等砖材之间填缝使用。\"},{\"name\":\"水泥\",\"productModel\":\"标号32.5\",\"brandName\":\"飞鹿体验\",\"brandID\":\"folder20138261029309087627570\",\"id\":\"be6e9ee8-388d-42a0-bce1-b842436a215f-ce\",\"count\":5,\"total\":122,\"unit\":\"公斤\",\"unitPrice\":\"面议\",\"totalPrice\":\"面议\",\"discounts\":\"可预约团购\",\"help\":\"水泥与中沙按一定的比例混合均匀，加水制成水泥砂浆，用于墙面、地面的平整处理；铺设墙砖、地砖也需要用到水泥。\"},{\"name\":\"中沙\",\"productModel\":\"中沙\",\"brandName\":\"飞鹿体验\",\"brandID\":\"folder20138261029309087627570\",\"id\":\"be6e9ee8-388d-42a0-bce1-b842436a215f-ms\",\"count\":15,\"total\":366,\"unit\":\"公斤\",\"unitPrice\":\"面议\",\"totalPrice\":\"面议\",\"discounts\":\"可预约团购\",\"help\":\"中沙用来和水泥搭配，用于墙面、地面的平整处理，也用来粉墙和贴瓷砖等。\"}]},{\"productModel\":\"常规\",\"brandName\":\"飞鹿体验\",\"brandID\":\"folder20138261029309087627570\",\"name\":\"壁纸\",\"recommend\":false,\"id\":\"4f4be1d7-18f5-43d8-839c-144236de4f82\",\"count\":7,\"total\":7,\"unit\":\"卷\",\"unitPrice\":\"面议\",\"totalPrice\":\"面议\",\"discounts\":\"可预约团购\",\"help\":\"\",\"info\":[{\"name\":\"壁纸基材\",\"productModel\":\"常规\",\"brandName\":\"飞鹿体验\",\"brandID\":\"folder20138261029309087627570\",\"id\":\"4f4be1d7-18f5-43d8-839c-144236de4f82-wbm\",\"count\":3,\"total\":3,\"unit\":\"套\",\"unitPrice\":\"面议\",\"totalPrice\":\"面议\",\"discounts\":\"可预约团购\",\"help\":\"\"},{\"name\":\"墙面腻子\",\"productModel\":\"常规\",\"brandName\":\"飞鹿体验\",\"brandID\":\"folder20138261029309087627570\",\"id\":\"4f4be1d7-18f5-43d8-839c-144236de4f82-wp\",\"count\":34,\"total\":34,\"unit\":\"平方米\",\"unitPrice\":\"面议\",\"totalPrice\":\"面议\",\"discounts\":\"可预约团购\",\"help\":\"给墙面刷乳胶漆涂料之前，对墙基面进行预处理的一种表面填充材料。\"}]},{\"productModel\":\"0\",\"brandName\":\"飞鹿体验\",\"brandID\":\"folder20138261029309087627570\",\"name\":\"吊顶\",\"recommend\":false,\"id\":\"436df70e-e9f4-44e3-8ab0-cf1600656f43\",\"count\":1,\"total\":9,\"unit\":\"平方米\",\"unitPrice\":\"面议\",\"totalPrice\":\"面议\",\"discounts\":\"可预约团购\",\"help\":\"\",\"info\":[]}],\"modelList\":{\"Furniture\":[{\"recommend\":false,\"id\":\"2a6b66c8-8b12-4a4b-9671-97a28e845aa2\",\"count\":1,\"brandName\":\"飞鹿体验\",\"brandID\":\"folder20138261029309087627570\",\"total\":1,\"unit\":\"个\",\"unitPrice\":1,\"totalPrice\":1,\"discounts\":\"可预约团购\",\"shopLocation\":\"\",\"help\":\"\",\"productModel\":\"1\",\"name\":\"双人沙发\"},{\"recommend\":false,\"id\":\"4ec5ba3f-75af-477e-81f2-172487c51ae2\",\"count\":1,\"brandName\":\"飞鹿体验\",\"brandID\":\"folder20138261029309087627570\",\"total\":1,\"unit\":\"个\",\"unitPrice\":\"面议\",\"totalPrice\":\"面议\",\"discounts\":\"可预约团购\",\"shopLocation\":\"\",\"help\":\"\",\"productModel\":\"0\",\"name\":\"茶几\"},{\"recommend\":false,\"id\":\"b0a41f4d-82fd-4b7b-8fb3-9b5b2d834ad8\",\"count\":1,\"brandName\":\"飞鹿体验\",\"brandID\":\"folder20138261029309087627570\",\"total\":1,\"unit\":\"个\",\"unitPrice\":\"面议\",\"totalPrice\":\"面议\",\"discounts\":\"可预约团购\",\"shopLocation\":\"\",\"help\":\"\",\"productModel\":\"常规\",\"name\":\"单人沙发\"}],\"Lighting\":[{\"recommend\":false,\"id\":\"27c82ef2-4b39-48c8-bba9-48d0eb3b4b7e\",\"count\":8,\"brandName\":\"飞鹿体验\",\"brandID\":\"folder20138261029309087627570\",\"total\":8,\"unit\":\"个\",\"unitPrice\":\"面议\",\"totalPrice\":\"面议\",\"discounts\":\"可预约团购\",\"shopLocation\":\"\",\"help\":\"\",\"productModel\":\"0\",\"name\":\"筒灯\"},{\"recommend\":false,\"id\":\"06d071fb-fb77-412a-b023-0c8452f3d7ec\",\"count\":1,\"brandName\":\"飞鹿体验\",\"brandID\":\"folder20138261029309087627570\",\"total\":1,\"unit\":\"个\",\"unitPrice\":\"面议\",\"totalPrice\":\"面议\",\"discounts\":\"可预约团购\",\"shopLocation\":\"\",\"help\":\"\",\"productModel\":\"0\",\"name\":\"吊灯\"}],\"Appliances\":[{\"recommend\":false,\"id\":\"a0704ca6-6203-48aa-9865-431fc8d87da9\",\"count\":1,\"brandName\":\"飞鹿体验\",\"brandID\":\"folder20138261029309087627570\",\"total\":1,\"unit\":\"个\",\"unitPrice\":\"面议\",\"totalPrice\":\"面议\",\"discounts\":\"可预约团购\",\"shopLocation\":\"\",\"help\":\"\",\"productModel\":\"常规\",\"name\":\"电视\"}],\"Cupboard\":[],\"Bathroom\":[],\"Metal\":[{\"recommend\":false,\"id\":\"bb85152f-d778-401e-abe8-cd32484d6edd\",\"count\":1,\"brandName\":\"飞鹿体验\",\"brandID\":\"folder20138261029309087627570\",\"total\":1,\"unit\":\"个\",\"unitPrice\":\"面议\",\"totalPrice\":\"面议\",\"discounts\":\"可预约团购\",\"shopLocation\":\"\",\"help\":\"\",\"productModel\":\"0\",\"name\":\"置物架\"},{\"recommend\":false,\"id\":\"897afbcc-7a60-4109-a53d-81eacd45626c\",\"count\":1,\"brandName\":\"飞鹿体验\",\"brandID\":\"folder20138261029309087627570\",\"total\":1,\"unit\":\"个\",\"unitPrice\":\"面议\",\"totalPrice\":\"面议\",\"discounts\":\"可预约团购\",\"shopLocation\":\"\",\"help\":\"\",\"productModel\":\"0\",\"name\":\"置物架\"}],\"Accessories\":[{\"recommend\":false,\"id\":\"552012b0-4326-45c4-99e7-0c8bc4cf4a99\",\"count\":1,\"brandName\":\"飞鹿体验\",\"brandID\":\"folder20138261029309087627570\",\"total\":1,\"unit\":\"个\",\"unitPrice\":1,\"totalPrice\":1,\"discounts\":\"可预约团购\",\"shopLocation\":\"\",\"help\":\"\",\"productModel\":\"1\",\"name\":\"地毯\"},{\"recommend\":false,\"id\":\"9ad4b057-74c3-4778-825b-a9f0aeb7c7a3\",\"count\":1,\"brandName\":\"飞鹿体验\",\"brandID\":\"folder20138261029309087627570\",\"total\":1,\"unit\":\"个\",\"unitPrice\":\"面议\",\"totalPrice\":\"面议\",\"discounts\":\"可预约团购\",\"shopLocation\":\"\",\"help\":\"\",\"productModel\":\"常规\",\"name\":\"摆件\"}]},\"manualList\":{\"isWaterproof\":false,\"wall1\":[{\"profession\":\"泥瓦工\",\"requirement\":\"拉毛，铲墙皮，基础处理，腻子两遍\",\"reason\":\"\",\"accessoryDesc\":\"\",\"workAmount\":34,\"unit\":\"平方米\",\"unitPrice\":60,\"productName\":\"基层处理\",\"id\":\"qiangmianjicengchuli\",\"totalPrice\":2040,\"detail\":[{\"profession\":\"泥瓦工\",\"requirement\":\"铲除原有表层腻子粉至基层\",\"reason\":\"一般毛坯房，就算有腻子也不可用，铲除原有腻子到水泥层，便于接下来做新腻子\",\"accessoryDesc\":\"\",\"workAmount\":34,\"unit\":\"平方米\",\"unitPrice\":7,\"totalPrice\":238,\"productName\":\"铲除原有墙皮腻子\",\"id\":\"wall_dimianjicengchuli_chanqiang\"},{\"profession\":\"泥瓦工\",\"requirement\":\"清理墙面→位置确定→粘贴墙布网格带或的确良布生态家园牌环保白乳胶粘贴\",\"reason\":\"墙体材质不同，各材质的膨胀率也不同，很容易出现墙体裂缝，所以要贴布处理，避免裂缝的产生。\",\"accessoryDesc\":\"网格带或的确良布、生态家园白乳胶\",\"workAmount\":34,\"unit\":\"平方米\",\"unitPrice\":19,\"totalPrice\":646,\"productName\":\"墙面贴布\",\"id\":\"wall_dimianjicengchuli_tiebufanglie\"},{\"profession\":\"泥瓦工\",\"requirement\":\"墙顶面铲除腻子后，用高强底层石膏找平处理;\",\"reason\":\"如果墙面不平整度大于5毫米，找平的腻子太厚会导致日后墙面开裂，因此要改用找平专用材料\\u201c粉刷石膏\\u201d来找平墙面\",\"accessoryDesc\":\"粉刷石膏\",\"workAmount\":34,\"unit\":\"平方米\",\"unitPrice\":15,\"totalPrice\":510,\"productName\":\"石膏找平\",\"id\":\"wall_dimianjicengchuli_zhaoping\"},{\"profession\":\"泥瓦工\",\"requirement\":\"选择贴墙纸,则需要先刷一层基模\",\"reason\":\"undefined\",\"accessoryDesc\":\"\",\"workAmount\":34,\"unit\":\"平方米\",\"unitPrice\":4,\"totalPrice\":136,\"productName\":\"刷基膜\",\"id\":\"wall_dimianjicengchuli_shuajimo\"},{\"profession\":\"泥瓦工\",\"requirement\":\"360号砂纸将腻子打磨平整\",\"reason\":\"\",\"accessoryDesc\":\"\",\"workAmount\":34,\"unit\":\"平方米\",\"unitPrice\":15,\"totalPrice\":510,\"productName\":\"墙面刷界面剂\",\"id\":\"wall_dimianjicengchuli_shazhidamo\"}]},{\"profession\":\"泥瓦工\",\"requirement\":\"\",\"reason\":\"\",\"accessoryDesc\":\"轻工辅料\",\"workAmount\":34,\"unit\":\"平方米\",\"unitPrice\":3.2,\"totalPrice\":109,\"productName\":\"贴壁纸\",\"id\":\"tiebizhi\"},{\"profession\":\"水电工\",\"requirement\":\"\",\"reason\":\"\",\"accessoryDesc\":\"\",\"workAmount\":\"\",\"unit\":\"米\",\"unitPrice\":0,\"totalPrice\":0,\"productName\":\"电改造\",\"id\":\"gaidian\"}],\"floor\":[{\"profession\":\"泥瓦工\",\"requirement\":\"1、先把下水口及地漏用塑料袋封好，扫净放水冲净地面泥土； 2、了解瓷砖的色泽及尺寸，计量地面尺寸，合理排列瓷砖； 3、地面1∶3的比例配比水泥沙浆干灰面铺底，砖背面用素水泥打浆铺贴或用湿１:３的水泥沙浆直接铺贴，厚度不超过4cm（根据地面平整度来定）地砖平整度2米之内误差3mm，空鼓率为5%\",\"reason\":\"\",\"accessoryDesc\":\"材料:钻牌32.5、过筛中沙\",\"workAmount\":8.2,\"unit\":\"平方米\",\"unitPrice\":35,\"totalPrice\":287,\"productName\":\"铺地砖\",\"id\":\"pudizhuan\"}],\"ceiling\":[{\"profession\":\"泥瓦工\",\"requirement\":\"刮腻子2-3遍，砂纸打磨平整\",\"reason\":\"\",\"accessoryDesc\":\"\",\"workAmount\":9,\"unit\":\"平方米\",\"unitPrice\":61.6,\"totalPrice\":555,\"productName\":\"基层处理\",\"detail\":[{\"profession\":\"泥瓦工\",\"requirement\":\"铲除原有表层腻子粉至基层\",\"reason\":\"一般毛坯房，就算有腻子也不可用，铲除原有腻子到水泥层，便于接下来做新腻子\",\"accessoryDesc\":\"\",\"workAmount\":9,\"unit\":\"平方米\",\"unitPrice\":7,\"totalPrice\":63,\"productName\":\"铲除原有墙皮腻子\",\"id\":\"ceiling_dingmianjicengchuli_dingmianchanqiang\"},{\"profession\":\"泥瓦工\",\"requirement\":\"清理顶面→位置确定→粘贴墙布网格带或的确良布生态家园牌环保白乳胶粘贴\",\"reason\":\"材质不同，各材质的膨胀率也不同，很容易出现裂缝，所以要贴布处理，避免裂缝的产生。\",\"accessoryDesc\":\"网格带或的确良布、生态家园白乳胶\",\"workAmount\":9,\"unit\":\"平方米\",\"unitPrice\":19,\"totalPrice\":171,\"productName\":\"顶面贴布\",\"id\":\"ceiling_dingmianjicengchuli_dingmiantiebu\"},{\"profession\":\"泥瓦工\",\"requirement\":\"顶面铲除腻子后，用高强底层石膏找平处理;\",\"reason\":\"如果顶面不平整度大于5毫米，找平的腻子太厚会导致日后顶面开裂，因此要改用找平专用材料\\u201c粉刷石膏\\u201d来找平顶面\",\"accessoryDesc\":\"粉刷石膏\",\"workAmount\":9,\"unit\":\"平方米\",\"unitPrice\":15,\"totalPrice\":135,\"productName\":\"石膏找平\",\"id\":\"ceiling_dingmianjicengchuli_shigouzhaoping\"},{\"profession\":\"泥瓦工\",\"requirement\":\"刮腻子2-3遍，砂纸打磨平整；阴阳角顺直\",\"reason\":\"腻子属于结合层，具有找平和粘结附着的作用\",\"accessoryDesc\":\"美巢\\u201c易呱平YGP800内墙耐水腻子或者YGP400\\u201d内墙腻子\",\"workAmount\":9,\"unit\":\"平方米\",\"unitPrice\":16,\"totalPrice\":144,\"productName\":\"顶面刮腻子\",\"id\":\"ceiling_dingmianjicengchuli_dingmianguanizi\"},{\"profession\":\"泥瓦工\",\"requirement\":\"顶面刷美巢墙锢一遍\",\"reason\":\"界面剂有固化作用，能够很好的固化原基础墙面，使找腻子平层与原基础连接更牢固，不容易脱落起皮，否则原基础找平层有松动\",\"accessoryDesc\":\"美巢地墙固\",\"workAmount\":9,\"unit\":\"平方米\",\"unitPrice\":4.6,\"totalPrice\":42,\"productName\":\"顶面刷界面剂\",\"id\":\"ceiling_dingmianjicengchuli_shuajiemianji\"}],\"id\":\"diaodingjicengchuli\"},{\"profession\":\"油漆工\",\"requirement\":\"滚刷底漆一遍，面漆两遍，（甲方提供墙漆，滚筒，羊毛刷。因滚筒羊毛刷是一次性的东西，谁买墙漆谁买滚筒羊毛刷）\",\"reason\":\"\",\"accessoryDesc\":\"轻工辅料\",\"workAmount\":9,\"unit\":\"平方米\",\"unitPrice\":25,\"totalPrice\":225,\"productName\":\"刷顶漆\",\"id\":\"shuaqi\"},{\"profession\":\"木工\",\"requirement\":\"石膏阴角线条安装、木龙骨石膏板\",\"reason\":\"\",\"accessoryDesc\":\"\",\"workAmount\":9,\"unit\":\"平方米\",\"unitPrice\":110,\"totalPrice\":990,\"productName\":\"吊顶\",\"id\":\"diaoding\"}],\"others\":[{\"profession\":\"水电工\",\"requirement\":\"\",\"reason\":\"隔音性好，结实性强，不易变形，贴完瓷砖后不易炸缝\",\"accessoryDesc\":\"钻牌32.5水泥、过筛中沙；红砖或轻体砖\",\"workAmount\":0,\"unit\":\"项\",\"unitPrice\":100,\"totalPrice\":0,\"productName\":\"五金安装\",\"id\":\"wujinanzhuang\"},{\"profession\":\"清洁工\",\"requirement\":\"\",\"reason\":\"\",\"accessoryDesc\":\"\",\"workAmount\":1,\"unit\":\"项\",\"unitPrice\":200,\"totalPrice\":200,\"productName\":\"垃圾清运\",\"id\":\"lajiqingyun\"}]},\"rTotalAmount\":2,\"yTotalAmount\":11909.7,\"mTotalAmount\":4406}","detail":true,"Success":true,"Time":307,"contenttype":"application/json","program":true}